{
	"__v" : NumberInt(0),
	"_id" : ObjectId("5e3240602147092f14dec583"),
	"msg" : "這是之前的對話",
	"name" : "Robby",
	"time" : 1580351584113
},
{
	"__v" : NumberInt(0),
	"_id" : ObjectId("5e3241f3bf0a1b250432bec4"),
	"msg" : "各位觀眾五個Ａ",
	"name" : "Ａ君",
	"time" : 1580351987317
},
{
	"__v" : NumberInt(0),
	"_id" : ObjectId("5e32422cbf0a1b250432bec5"),
	"msg" : "Ｂ級美食最高！",
	"name" : "Ｂ君",
	"time" : 1580352044154
},
{
	"__v" : NumberInt(0),
	"_id" : ObjectId("5e32424fbf0a1b250432bec6"),
	"msg" : "Ｃ的果凍",
	"name" : "Ｃ君",
	"time" : 1580352079744
},
{
	"__v" : NumberInt(0),
	"_id" : ObjectId("5e3243bf8d29ae17644b3513"),
	"msg" : "Ｄ　ＦＯＲ　ＤＯＧ",
	"name" : "Ｄ君",
	"time" : 1580352447375
},
{
	"__v" : NumberInt(0),
	"_id" : ObjectId("5e3244f997272e135c696c38"),
	"msg" : "大家好~!",
	"name" : "Teddy",
	"time" : 1580352761582
},
{
	"__v" : NumberInt(0),
	"_id" : ObjectId("5e32456097272e135c696c39"),
	"msg" : "我是誰?",
	"name" : "Robby",
	"time" : 1580352864240
},
{
	"__v" : NumberInt(0),
	"_id" : ObjectId("5e32458497272e135c696c3a"),
	"msg" : "為了防止世界的破壞",
	"name" : "武藏",
	"time" : 1580352900374
},
{
	"__v" : NumberInt(0),
	"_id" : ObjectId("5e32459d97272e135c696c3b"),
	"msg" : "為了守護世界的和平",
	"name" : "小次郎",
	"time" : 1580352925483
},
{
	"__v" : NumberInt(0),
	"_id" : ObjectId("5e3245af97272e135c696c3c"),
	"msg" : "貫徹愛與真實的邪惡",
	"name" : "武藏",
	"time" : 1580352943985
},
{
	"__v" : NumberInt(0),
	"_id" : ObjectId("5e3245b997272e135c696c3d"),
	"msg" : "可愛又迷人的反派角色",
	"name" : "小次郎",
	"time" : 1580352953185
},
{
	"__v" : NumberInt(0),
	"_id" : ObjectId("5e3245c797272e135c696c3e"),
	"msg" : "武藏！",
	"name" : "武藏",
	"time" : 1580352967257
},
{
	"__v" : NumberInt(0),
	"_id" : ObjectId("5e3245ce97272e135c696c3f"),
	"msg" : "小次郎！",
	"name" : "小次郎",
	"time" : 1580352974990
},
{
	"__v" : NumberInt(0),
	"_id" : ObjectId("5e32635a97272e135c696c40"),
	"msg" : "我們是穿梭在銀行的火箭隊！",
	"name" : "武藏",
	"time" : 1580360538122
},
{
	"__v" : NumberInt(0),
	"_id" : ObjectId("5e32637b97272e135c696c41"),
	"msg" : "白色的明天再等著我們！",
	"name" : "小次郎",
	"time" : 1580360571658
},
{
	"__v" : NumberInt(0),
	"_id" : ObjectId("5e32638497272e135c696c42"),
	"msg" : "喵喵",
	"name" : "喵喵",
	"time" : 1580804406236
},
{
	"__v" : NumberInt(0),
	"_id" : ObjectId("5e33df3e1ae4881b384f3eee"),
	"msg" : "你好",
	"name" : "Robby",
	"time" : 1580457790496
},
{
	"__v" : NumberInt(0),
	"_id" : ObjectId("5e3907f07077cb21b4c47e52"),
	"msg" : "你好",
	"name" : "小次郎",
	"time" : 1580795888537
},
